{
  "input_path": "/home/yhyoon/experiment/pldi2023_final/pldi2023-artifact/bench/bitvec/deobfusc/target_258.sl",
  "problem_name": "target_258",
  "start_time": "23.03.22.23:37:42",
  "total_time": 35.11035108566284,
  "options": [
    [ "debug", "false" ],
    [ "init_comp_size", "1" ],
    [ "max_comp_size", "128" ],
    [ "gamma_size", "8" ],
    [ "topdown", "hole2" ],
    [ "pruning", "abstsem" ],
    [ "cegis_jump", "true" ],
    [ "no_backward", "false" ],
    [ "force_full_analysis", "false" ],
    [ "dt_predicate_order", "own_heuristic" ]
  ],
  "cegis_solver_count": 0,
  "cegis_solver_call_time": 0.0,
  "cegis_iters": [
    {
      "created_top": [ [ 0, 3 ], [ 1, 2 ], [ 2, 6 ] ],
      "created_sub": [ [ 0, 25482 ], [ 1, 27 ] ],
      "created_components": 84000
    },
    {
      "created_top": [ [ 0, 3 ], [ 1, 2 ], [ 2, 6 ] ],
      "created_sub": [ [ 0, 10757100 ], [ 1, 146994 ] ],
      "created_components": 76856
    },
    {
      "created_top": [ [ 0, 3 ], [ 1, 2 ], [ 2, 6 ] ],
      "created_sub": [ [ 0, 405494 ], [ 1, 26896 ] ],
      "created_components": 12906
    }
  ],
  "final_io_pairs": 3,
  "final_max_component_size": 8,
  "final_component_count": 84000,
  "found_solution": "(define-fun deobfucated ( (c (BitVec 64)) (b (BitVec 64)) (d (BitVec 64))) (BitVec 64) (bvor (bvand (bvneg b) (bvsub b (bvmul c b))) (bvsub c d)))",
  "solution_size": 12,
  "total_composed": [ [ 0, 11188085 ], [ 1, 173923 ], [ 2, 18 ] ],
  "component_generation_time": 3.019315004348755,
  "component_search_table_build_time": 1.0953092575073242,
  "prune": {
    "method": "abstsem",
    "count": 173941,
    "time": 3.2796645164489746,
    "infeasible": 108210,
    "search_infeasible": 65438,
    "search_useful": 1,
    "approx_reduced_incomplete": 108210,
    "approx_reduced_complete": 6610340090
  }
}